{
  "generatedAt": "2026-06-24T06:05:55.455Z",
  "windowDays": 7,
  "threshold": 2,
  "lines": [
    {
      "line": "FLYG",
      "samples": 30,
      "onTime": 30,
      "totalDelayMin": 0,
      "onTimePct": 100,
      "avgDelayMin": 0
    },
    {
      "line": "5",
      "samples": 23,
      "onTime": 23,
      "totalDelayMin": 0,
      "onTimePct": 100,
      "avgDelayMin": 0
    },
    {
      "line": "10",
      "samples": 92,
      "onTime": 91,
      "totalDelayMin": 20,
      "onTimePct": 98.9,
      "avgDelayMin": 0.22
    },
    {
      "line": "63",
      "samples": 130,
      "onTime": 125,
      "totalDelayMin": 59,
      "onTimePct": 96.2,
      "avgDelayMin": 0.45
    },
    {
      "line": "758",
      "samples": 23,
      "onTime": 22,
      "totalDelayMin": 9,
      "onTimePct": 95.7,
      "avgDelayMin": 0.39
    },
    {
      "line": "61",
      "samples": 279,
      "onTime": 258,
      "totalDelayMin": 149,
      "onTimePct": 92.5,
      "avgDelayMin": 0.53
    },
    {
      "line": "12",
      "samples": 93,
      "onTime": 85,
      "totalDelayMin": 73,
      "onTimePct": 91.4,
      "avgDelayMin": 0.78
    },
    {
      "line": "4",
      "samples": 129,
      "onTime": 116,
      "totalDelayMin": 115,
      "onTimePct": 89.9,
      "avgDelayMin": 0.89
    },
    {
      "line": "1",
      "samples": 269,
      "onTime": 241,
      "totalDelayMin": 232,
      "onTimePct": 89.6,
      "avgDelayMin": 0.86
    },
    {
      "line": "2",
      "samples": 67,
      "onTime": 59,
      "totalDelayMin": 63,
      "onTimePct": 88.1,
      "avgDelayMin": 0.94
    },
    {
      "line": "X",
      "samples": 32,
      "onTime": 28,
      "totalDelayMin": 24,
      "onTimePct": 87.5,
      "avgDelayMin": 0.75
    },
    {
      "line": "60",
      "samples": 95,
      "onTime": 83,
      "totalDelayMin": 101,
      "onTimePct": 87.4,
      "avgDelayMin": 1.06
    },
    {
      "line": "8",
      "samples": 92,
      "onTime": 80,
      "totalDelayMin": 89,
      "onTimePct": 87,
      "avgDelayMin": 0.97
    },
    {
      "line": "X5",
      "samples": 43,
      "onTime": 37,
      "totalDelayMin": 56,
      "onTimePct": 86,
      "avgDelayMin": 1.3
    },
    {
      "line": "3",
      "samples": 229,
      "onTime": 197,
      "totalDelayMin": 240,
      "onTimePct": 86,
      "avgDelayMin": 1.05
    },
    {
      "line": "X4",
      "samples": 71,
      "onTime": 60,
      "totalDelayMin": 86,
      "onTimePct": 84.5,
      "avgDelayMin": 1.21
    },
    {
      "line": "9",
      "samples": 178,
      "onTime": 145,
      "totalDelayMin": 247,
      "onTimePct": 81.5,
      "avgDelayMin": 1.39
    },
    {
      "line": "18",
      "samples": 296,
      "onTime": 221,
      "totalDelayMin": 463,
      "onTimePct": 74.7,
      "avgDelayMin": 1.56
    },
    {
      "line": "6",
      "samples": 362,
      "onTime": 249,
      "totalDelayMin": 812,
      "onTimePct": 68.8,
      "avgDelayMin": 2.24
    },
    {
      "line": "7",
      "samples": 72,
      "onTime": 49,
      "totalDelayMin": 152,
      "onTimePct": 68.1,
      "avgDelayMin": 2.11
    },
    {
      "line": "11",
      "samples": 279,
      "onTime": 172,
      "totalDelayMin": 634,
      "onTimePct": 61.6,
      "avgDelayMin": 2.27
    },
    {
      "line": "X2",
      "samples": 136,
      "onTime": 83,
      "totalDelayMin": 303,
      "onTimePct": 61,
      "avgDelayMin": 2.23
    },
    {
      "line": "25",
      "samples": 84,
      "onTime": 51,
      "totalDelayMin": 240,
      "onTimePct": 60.7,
      "avgDelayMin": 2.86
    },
    {
      "line": "X6",
      "samples": 15,
      "onTime": 7,
      "totalDelayMin": 54,
      "onTimePct": 46.7,
      "avgDelayMin": 3.6
    }
  ]
}