{
  "generatedAt": "2026-07-16T03:53:18.837Z",
  "windowDays": 7,
  "threshold": 2,
  "lines": [
    {
      "line": "5",
      "samples": 122,
      "onTime": 122,
      "totalDelayMin": 1,
      "onTimePct": 100,
      "avgDelayMin": 0.01
    },
    {
      "line": "FLYG",
      "samples": 51,
      "onTime": 51,
      "totalDelayMin": 0,
      "onTimePct": 100,
      "avgDelayMin": 0
    },
    {
      "line": "63",
      "samples": 206,
      "onTime": 202,
      "totalDelayMin": 76,
      "onTimePct": 98.1,
      "avgDelayMin": 0.37
    },
    {
      "line": "10",
      "samples": 141,
      "onTime": 135,
      "totalDelayMin": 67,
      "onTimePct": 95.7,
      "avgDelayMin": 0.48
    },
    {
      "line": "61",
      "samples": 450,
      "onTime": 423,
      "totalDelayMin": 213,
      "onTimePct": 94,
      "avgDelayMin": 0.47
    },
    {
      "line": "758",
      "samples": 37,
      "onTime": 34,
      "totalDelayMin": 5,
      "onTimePct": 91.9,
      "avgDelayMin": 0.14
    },
    {
      "line": "2",
      "samples": 107,
      "onTime": 96,
      "totalDelayMin": 97,
      "onTimePct": 89.7,
      "avgDelayMin": 0.91
    },
    {
      "line": "8",
      "samples": 140,
      "onTime": 125,
      "totalDelayMin": 120,
      "onTimePct": 89.3,
      "avgDelayMin": 0.86
    },
    {
      "line": "12",
      "samples": 159,
      "onTime": 138,
      "totalDelayMin": 193,
      "onTimePct": 86.8,
      "avgDelayMin": 1.21
    },
    {
      "line": "4",
      "samples": 225,
      "onTime": 193,
      "totalDelayMin": 284,
      "onTimePct": 85.8,
      "avgDelayMin": 1.26
    },
    {
      "line": "114",
      "samples": 7,
      "onTime": 6,
      "totalDelayMin": 3,
      "onTimePct": 85.7,
      "avgDelayMin": 0.43
    },
    {
      "line": "9",
      "samples": 292,
      "onTime": 243,
      "totalDelayMin": 393,
      "onTimePct": 83.2,
      "avgDelayMin": 1.35
    },
    {
      "line": "X",
      "samples": 32,
      "onTime": 25,
      "totalDelayMin": 51,
      "onTimePct": 78.1,
      "avgDelayMin": 1.59
    },
    {
      "line": "1",
      "samples": 420,
      "onTime": 323,
      "totalDelayMin": 706,
      "onTimePct": 76.9,
      "avgDelayMin": 1.68
    },
    {
      "line": "X4",
      "samples": 117,
      "onTime": 89,
      "totalDelayMin": 183,
      "onTimePct": 76.1,
      "avgDelayMin": 1.56
    },
    {
      "line": "3",
      "samples": 393,
      "onTime": 293,
      "totalDelayMin": 699,
      "onTimePct": 74.6,
      "avgDelayMin": 1.78
    },
    {
      "line": "X5",
      "samples": 74,
      "onTime": 55,
      "totalDelayMin": 141,
      "onTimePct": 74.3,
      "avgDelayMin": 1.91
    },
    {
      "line": "18",
      "samples": 489,
      "onTime": 363,
      "totalDelayMin": 853,
      "onTimePct": 74.2,
      "avgDelayMin": 1.74
    },
    {
      "line": "6",
      "samples": 595,
      "onTime": 435,
      "totalDelayMin": 1121,
      "onTimePct": 73.1,
      "avgDelayMin": 1.88
    },
    {
      "line": "X2",
      "samples": 241,
      "onTime": 175,
      "totalDelayMin": 435,
      "onTimePct": 72.6,
      "avgDelayMin": 1.8
    },
    {
      "line": "60",
      "samples": 143,
      "onTime": 103,
      "totalDelayMin": 252,
      "onTimePct": 72,
      "avgDelayMin": 1.76
    },
    {
      "line": "25",
      "samples": 116,
      "onTime": 79,
      "totalDelayMin": 221,
      "onTimePct": 68.1,
      "avgDelayMin": 1.91
    },
    {
      "line": "7",
      "samples": 117,
      "onTime": 71,
      "totalDelayMin": 351,
      "onTimePct": 60.7,
      "avgDelayMin": 3
    },
    {
      "line": "11",
      "samples": 439,
      "onTime": 264,
      "totalDelayMin": 1337,
      "onTimePct": 60.1,
      "avgDelayMin": 3.05
    },
    {
      "line": "X6",
      "samples": 85,
      "onTime": 36,
      "totalDelayMin": 296,
      "onTimePct": 42.4,
      "avgDelayMin": 3.48
    }
  ]
}